mcache/__init__.py
mcache/_filecache.py
mcache/_memcache.py
mcache/cache.py
mcache/version.py
tests/__init__.py
tests/mcache_tests/__init__.py
tests/mcache_tests/test_filecache.py
tests/mcache_tests/test_key.py
tests/mcache_tests/test_memcache.py
mcache-1.0.0.dist-info/LICENSE
mcache-1.0.0.dist-info/METADATA
mcache-1.0.0.dist-info/WHEEL
mcache-1.0.0.dist-info/top_level.txt
mcache-1.0.0.dist-info/RECORD
