Metadata-Version: 2.1
Name: mcache
Version: 1.0.0
Summary: Async ready Multi Caching Library.
Home-page: https://github.com/marirs/mcache/
Author: Sriram G
Author-email: marirs@gmail.com
License: MIT
Keywords: Python 3,caching,memcache,filecache,redis,async,asyncio,cache
Platform: UNKNOWN
Classifier: Development Status :: 5 - Production/Stable
Classifier: Environment :: Console
Classifier: Intended Audience :: Developers
Classifier: License :: OSI Approved :: MIT License
Classifier: Operating System :: MacOS :: MacOS X
Classifier: Operating System :: POSIX :: Linux
Classifier: Programming Language :: Python :: 3.6
Classifier: Programming Language :: Python :: 3.7
Classifier: Programming Language :: Python :: 3.8
Classifier: Topic :: Internet
Classifier: Topic :: Software Development :: Libraries :: Python Modules
Requires-Python: >=3.6
Requires-Dist: pymemcache (>=3.2.0)
